mcp_habitica/__init__.py
mcp_habitica/habitica_client.py
mcp_habitica/server.py
mcp_habitica-0.2.2.dist-info/METADATA
mcp_habitica-0.2.2.dist-info/WHEEL
mcp_habitica-0.2.2.dist-info/entry_points.txt
mcp_habitica-0.2.2.dist-info/licenses/LICENSE
mcp_habitica-0.2.2.dist-info/RECORD
