Metadata-Version: 2.4
Name: mcp-habitica
Version: 0.2.2
Summary: MCP server for Habitica task and tag management
Project-URL: Homepage, https://github.com/pemtajo/mcp-habitica
Project-URL: Repository, https://github.com/pemtajo/mcp-habitica
Project-URL: Issues, https://github.com/pemtajo/mcp-habitica/issues
Author-email: Pedro Matias <pedrom.araujo@outlook.com>
License: MIT
License-File: LICENSE
Keywords: habitica,mcp,productivity,task-management
Classifier: Development Status :: 4 - Beta
Classifier: Intended Audience :: Developers
Classifier: License :: OSI Approved :: MIT License
Classifier: Programming Language :: Python :: 3
Classifier: Programming Language :: Python :: 3.10
Classifier: Programming Language :: Python :: 3.11
Classifier: Programming Language :: Python :: 3.12
Requires-Python: >=3.10
Requires-Dist: httpx>=0.27.0
Requires-Dist: mcp>=1.0.0
Provides-Extra: dev
Requires-Dist: pytest-asyncio>=0.23.0; extra == 'dev'
Requires-Dist: pytest>=8.0.0; extra == 'dev'
